{
  "default_model": "medium_april",
  "models": {
    "medium_april": {
      "model": "trained_whisper_medium_april_2026_ct2",
      "compute_type": "float16",
      "device": "cuda",
      "transcribe": {
        "task": "transcribe",
        "language": "en",
        "beam_size": 1,
        "word_timestamps": false,
        "condition_on_previous_text": false,
        "vad_filter": false,
        "temperature": 0.0
      }
    },

    "medium_april_tweaked": {
      "model": "trained_whisper_medium_april_2026_ct2",
      "compute_type": "float16",
      "device": "cuda",
      "transcribe": {
        "task": "transcribe",
        "language": "en",
        "beam_size": 3,
        "word_timestamps": false,
        "condition_on_previous_text": false,
        "vad_filter": true,
        "initial_prompt": "Police and fire radio traffic. Numbers, addresses, street names, 10-codes, license plates, call signs, dispatch terminology.",
        "temperature": 0.0
      }
    },

    "small_april": {
      "model": "/home/ned/models/trained_whisper_small_lora_merged_ct2",
      "compute_type": "float16",
      "device": "cuda",
      "transcribe": {
        "task": "transcribe",
        "language": "en",
        "beam_size": 4,
        "word_timestamps": false,
        "condition_on_previous_text": false,
        "vad_filter": true,
        "initial_prompt": "Police and fire radio traffic. Numbers, addresses, street names, 10-codes, license plates, call signs, dispatch terminology.",
        "temperature": 0.0
      }
    },
    "large": {
      "model": "trained_whisper_large_d040126_ct2",
      "compute_type": "float16",
      "device": "cuda"
    },
    "medium_feb": {
      "model": "trained_whisper_medium_d022526_ct2_v2",
      "compute_type": "float16",
      "device": "cuda"
    }
  }
}